pyogg/__init__.py
pyogg/flac.py
pyogg/libFLAC.dll
pyogg/libogg.dll
pyogg/library_loader.py
pyogg/libvorbis.dll
pyogg/libvorbisfile.dll
pyogg/ogg.py
pyogg/opus.dll
pyogg/opus.py
pyogg/opusenc.dll
pyogg/opusfile.dll
pyogg/vorbis.py
PyOgg-0.6.14a1.dist-info/COPYING
PyOgg-0.6.14a1.dist-info/LICENSE
PyOgg-0.6.14a1.dist-info/METADATA
PyOgg-0.6.14a1.dist-info/WHEEL
PyOgg-0.6.14a1.dist-info/top_level.txt
PyOgg-0.6.14a1.dist-info/RECORD
