Metadata-Version: 2.1
Name: PyOgg
Version: 0.6.14a1
Summary: Xiph.org's Ogg Vorbis, Opus and FLAC for Python
Home-page: https://github.com/Zuzu-Typ/PyOgg
Author: Zuzu_Typ
Author-email: zuzu.typ@gmail.com
License: BSD 3-clause "New" or "Revised"
Keywords: Xiph ogg vorbis opus flac sound playback audio
Platform: UNKNOWN
Classifier: Development Status :: 3 - Alpha
Classifier: Intended Audience :: Developers
Classifier: Topic :: Multimedia :: Sound/Audio
Classifier: License :: OSI Approved :: BSD License
Classifier: Programming Language :: Python :: 2
Classifier: Programming Language :: Python :: 2.7
Classifier: Programming Language :: Python :: 3
Classifier: Programming Language :: Python :: 3.3
Classifier: Programming Language :: Python :: 3.4
Classifier: Programming Language :: Python :: 3.5
Classifier: Programming Language :: Python :: 3.6
Classifier: Programming Language :: Python :: 3.7
Classifier: Programming Language :: Python :: 3.8
